[{"sn":101,"type":1,"pageRegion":"1,2","caveSn":"6,5,5,4,3,2,2,2,2"},{"sn":102,"type":1,"pageRegion":"3,10","caveSn":"5,4,4,3,2,2,2,2,2"},{"sn":103,"type":1,"pageRegion":"11,50","caveSn":"4,3,3,2,2,2,2,2,2"},{"sn":104,"type":1,"pageRegion":"51,800","caveSn":"3,2,2,1,1,1,1,1,1"},{"sn":201,"type":2,"pageRegion":"1,2","caveSn":"8,7,7,6,5,4,4,4,4"},{"sn":202,"type":2,"pageRegion":"3,10","caveSn":"7,6,5,5,4,3,3,3,3"},{"sn":203,"type":2,"pageRegion":"11,50","caveSn":"6,5,5,4,4,3,3,3,3"},{"sn":204,"type":2,"pageRegion":"51,100","caveSn":"5,4,4,4,4,3,3,3,3"}]